aws_connector/__init__.py
aws_connector/account_config.py
aws_connector/connector.py
aws_connector/version.py
aws_connector-0.2.10.dist-info/LICENSE
aws_connector-0.2.10.dist-info/METADATA
aws_connector-0.2.10.dist-info/WHEEL
aws_connector-0.2.10.dist-info/top_level.txt
aws_connector-0.2.10.dist-info/RECORD
