Metadata-Version: 2.1
Name: aws-connector
Version: 0.2.10
Summary: AWS connector switch-role tool from central IAM account.
Author-email: Mick Gortenmulder <mickgortenmulder@gmail.com>
Maintainer-email: Mick Gortenmulder <mickgortenmulder@gmail.com>
License: Copyright (c) 2018 The Python Packaging Authority        
Project-URL: Homepage, https://github.com/mickgortenmulder/aws-connector
Project-URL: Bug Tracker, https://github.com/mickgortenmulder/aws-connector/issues
Requires-Python: >=3.9
License-File: LICENSE
